powerwallstats/__init__.py
powerwallstats/powerwallstats.py
powerwallstats-1.0.1.dist-info/LICENSE
powerwallstats-1.0.1.dist-info/METADATA
powerwallstats-1.0.1.dist-info/WHEEL
powerwallstats-1.0.1.dist-info/top_level.txt
powerwallstats-1.0.1.dist-info/RECORD
