Metadata-Version: 2.1
Name: powerwallstats
Version: 1.0.1
Summary: powerwallstats: python library to read statistics from a Powerwall 2 gateway
Home-page: https://github.com/swm11/powerwallstats
Author: Simon Moore
License: BSD 2-Clause
Platform: UNKNOWN
Requires-Python: >=3.6
Requires-Dist: requests
